convenient_datascience_tools/__init__.py
convenient_datascience_tools/tools/__init__.py
convenient_datascience_tools/tools/pandas.py
convenient_datascience_tools-0.0.9.dist-info/METADATA
convenient_datascience_tools-0.0.9.dist-info/WHEEL
convenient_datascience_tools-0.0.9.dist-info/top_level.txt
convenient_datascience_tools-0.0.9.dist-info/RECORD
